easyvalidator/__init__.py
easyvalidator/base_functions.py
easyvalidator/base_rules.py
easyvalidator/rule_factory.py
easyvalidator/validator.py
tests/__init__.py
tests/body_validator_test.py
easy_validator-0.0.1.dist-info/LICENSE
easy_validator-0.0.1.dist-info/METADATA
easy_validator-0.0.1.dist-info/WHEEL
easy_validator-0.0.1.dist-info/top_level.txt
easy_validator-0.0.1.dist-info/RECORD
