Metadata-Version: 2.1
Name: easy-validator
Version: 0.0.1
Summary: A package for easy json validation.
Home-page: https://github.com/brworkit/python-package-easy-validator.git
Author: brworkit
Author-email: brworkit@gmail.com
License: UNKNOWN
Platform: UNKNOWN
Classifier: Programming Language :: Python :: 3
Classifier: License :: OSI Approved :: MIT License
Classifier: Operating System :: OS Independent
Requires-Python: >=3.6
